oobeya/__init__.py
oobeya/client.py
oobeya/exceptions.py
oobeya/models.py
oobeya/utils.py
oobeya/resources/__init__.py
oobeya/resources/api_keys.py
oobeya/resources/bulk_operations.py
oobeya/resources/defect_detection.py
oobeya/resources/deployments.py
oobeya/resources/external_test.py
oobeya/resources/git_analysis.py
oobeya/resources/members.py
oobeya/resources/organization_level.py
oobeya/resources/qwiser.py
oobeya/resources/reports.py
oobeya/resources/system.py
oobeya/resources/team_score_cards.py
oobeya/resources/teams.py
oobeya/resources/users.py
oobeya-0.1.0.dist-info/METADATA
oobeya-0.1.0.dist-info/WHEEL
oobeya-0.1.0.dist-info/licenses/LICENSE
oobeya-0.1.0.dist-info/RECORD
