Metadata-Version: 2.4
Name: oobeya
Version: 0.1.0
Summary: Python client library for Oobeya API - Software Engineering Intelligence Platform
Project-URL: Homepage, https://github.com/fajfer/oobeya
Project-URL: Documentation, https://github.com/fajfer/oobeya#readme
Project-URL: Repository, https://github.com/fajfer/oobeya
Project-URL: Issues, https://github.com/fajfer/oobeya/issues
Author-email: Damian Fajfer <damian@fajfer.org>
License: EUPL-1.2
License-File: LICENSE
Keywords: api,client,dora,engineering,metrics,oobeya
Classifier: Development Status :: 3 - Alpha
Classifier: Intended Audience :: Developers
Classifier: License :: OSI Approved :: European Union Public Licence 1.2 (EUPL 1.2)
Classifier: Programming Language :: Python :: 3
Classifier: Programming Language :: Python :: 3.12
Classifier: Programming Language :: Python :: 3.13
Classifier: Topic :: Software Development :: Libraries :: Python Modules
Requires-Python: >=3.12
Requires-Dist: python-dateutil>=2.8.2
Requires-Dist: requests>=2.31.0
Provides-Extra: dev
Requires-Dist: black>=23.7.0; extra == 'dev'
Requires-Dist: flake8>=6.1.0; extra == 'dev'
Requires-Dist: mypy>=1.5.0; extra == 'dev'
Requires-Dist: pytest-cov>=4.1.0; extra == 'dev'
Requires-Dist: pytest-mock>=3.11.1; extra == 'dev'
Requires-Dist: pytest>=7.4.0; extra == 'dev'
Requires-Dist: types-python-dateutil>=2.8.19; extra == 'dev'
Requires-Dist: types-requests>=2.31.0; extra == 'dev'
